flatnest/__init__.py
flatnest/flatnest.py
flatnest-1.0.5.dist-info/LICENSE
flatnest-1.0.5.dist-info/METADATA
flatnest-1.0.5.dist-info/WHEEL
flatnest-1.0.5.dist-info/top_level.txt
flatnest-1.0.5.dist-info/RECORD
