Metadata-Version: 2.1
Name: flatnest
Version: 1.0.5
Summary: Algorithms for traversing/flattening/constructing nested list structures
Home-page: https://github.com/mmiguel6288code/flatnest
Author: Matthew Miguel
Author-email: mmiguel6288code@gmail.com
Maintainer: Matthew Miguel
Maintainer-email: mmiguel6288code@gmail.com
License: MIT
Keywords: lists,list,depth first search,dfs,bfs,breadth first search,flatten,flat,pattern
Platform: UNKNOWN
Classifier: Intended Audience :: Developers
Classifier: License :: OSI Approved :: MIT License
Classifier: Natural Language :: English
Classifier: Operating System :: OS Independent
Classifier: Programming Language :: Python :: 2.7
Classifier: Programming Language :: Python :: 3.5
Classifier: Programming Language :: Python :: Implementation :: CPython
